odoo/addons/project_task_related/README.rst
odoo/addons/project_task_related/__init__.py
odoo/addons/project_task_related/__manifest__.py
odoo/addons/project_task_related/i18n/es.po
odoo/addons/project_task_related/i18n/it.po
odoo/addons/project_task_related/i18n/project_task_related.pot
odoo/addons/project_task_related/models/__init__.py
odoo/addons/project_task_related/models/project_task.py
odoo/addons/project_task_related/readme/CONTRIBUTORS.md
odoo/addons/project_task_related/readme/DESCRIPTION.md
odoo/addons/project_task_related/static/description/icon.png
odoo/addons/project_task_related/static/description/index.html
odoo/addons/project_task_related/tests/__init__.py
odoo/addons/project_task_related/tests/test_project_task_related.py
odoo/addons/project_task_related/views/project_task_views_related.xml
odoo_addon_project_task_related-17.0.1.0.3.dist-info/METADATA
odoo_addon_project_task_related-17.0.1.0.3.dist-info/WHEEL
odoo_addon_project_task_related-17.0.1.0.3.dist-info/top_level.txt
odoo_addon_project_task_related-17.0.1.0.3.dist-info/RECORD
